_libfstapi.abi3.so
pylibfst/__init__.py
pylibfst/helpers.py
pylibfst/libfstapi.cdef
pylibfst/libfstapi_build.py
pylibfst-0.2.1.dist-info/METADATA
pylibfst-0.2.1.dist-info/WHEEL
pylibfst-0.2.1.dist-info/top_level.txt
pylibfst-0.2.1.dist-info/RECORD
pylibfst-0.2.1.dist-info/licenses/COPYING
pylibfst-0.2.1.dist-info/licenses/LICENSE-fst
pylibfst-0.2.1.dist-info/licenses/LICENSE-fst-FastLZ
pylibfst-0.2.1.dist-info/licenses/LICENSE-fst-LZ4
pylibfst-0.2.1.dist-info/licenses/LICENSE-pylibfst
