Metadata-Version: 2.4
Name: pylibfst
Version: 0.2.1
Summary: Handling of Fast Signal Traces (fst) in Python
Home-page: https://github.com/mschlaegl/pylibfst
Author: Manfred SCHLAEGL, fst C implementation: Tony Bybell
Author-email: manfred.schlaegl@gmx.at
Keywords: fst,eda,gtkwave,vcd
Classifier: Topic :: Scientific/Engineering :: Electronic Design Automation (EDA)
Classifier: Development Status :: 4 - Beta
Classifier: Intended Audience :: Developers
Classifier: License :: OSI Approved :: MIT License
Classifier: License :: OSI Approved :: BSD License
Classifier: Programming Language :: Python :: 3
Classifier: Programming Language :: Python :: 3.8
Classifier: Programming Language :: Python :: 3.9
Classifier: Programming Language :: Python :: 3.10
Classifier: Programming Language :: Python :: 3 :: Only
Classifier: Operating System :: Unix
License-File: LICENSE-fst
License-File: LICENSE-fst-FastLZ
License-File: LICENSE-fst-LZ4
License-File: LICENSE-pylibfst
License-File: COPYING
Requires-Dist: cffi>=1.15.0
Dynamic: author
Dynamic: author-email
Dynamic: classifier
Dynamic: description
Dynamic: description-content-type
Dynamic: home-page
Dynamic: keywords
Dynamic: license-file
Dynamic: requires-dist
Dynamic: summary
